LICENSE
MANIFEST.in
README.rst
setup.cfg
setup.py
django_transfer/__init__.py
django_transfer/models.py
django_transfer/settings.py
django_transfer/tests.py
django_transfer/urls.py
django_transfer/views.py
django_transfer/wsgi.py
django_transfer.egg-info/PKG-INFO
django_transfer.egg-info/SOURCES.txt
django_transfer.egg-info/dependency_links.txt
django_transfer.egg-info/requires.txt
django_transfer.egg-info/top_level.txt