Metadata-Version: 1.1
Name: django-transfer
Version: 0.3
Summary: A django application that offloads file transfers to a downstream proxy.
Home-page: http://github.com/smartfile/django-transfer/
Author: Travis Cunningham
Author-email: tcunningham@smartfile.com
License: MIT
Platform: UNKNOWN
Classifier: Development Status :: 4 - Beta
Classifier: Intended Audience :: Developers
Classifier: Operating System :: OS Independent
Classifier: Programming Language :: Python :: 2
Classifier: Programming Language :: Python :: 3
Classifier: Topic :: Software Development :: Libraries :: Python Modules
